py_whelk.libs/libgcc_s-2d945d6c.so.1
pywhelk/__init__.py
pywhelk/pywhelk/__init__.py
pywhelk/pywhelk/ffi.py
pywhelk/pywhelk/libpywhelk.so
py_whelk-0.1.0.dist-info/METADATA
py_whelk-0.1.0.dist-info/WHEEL
py_whelk-0.1.0.dist-info/RECORD
py_whelk-0.1.0.dist-info/licenses/COPYING
py_whelk-0.1.0.dist-info/licenses/COPYING.lesser
