Metadata-Version: 2.4
Name: py-whelk
Version: 0.1.0
Classifier: Programming Language :: Rust
Classifier: Programming Language :: Python :: Implementation :: CPython
Classifier: Programming Language :: Python :: Implementation :: PyPy
Requires-Dist: cffi
Requires-Dist: py-horned-owl>=1.3.0.dev1
License-File: COPYING
License-File: COPYING.lesser
Summary: Wrapper arround whelk-rs for integration with py-horned-owl
Author: Björn Gehrke <bjoern.gehrke+pywhelk@uzh.ch>
Author-email: Björn Gehrke <bjoern.gehrke+pywhelk@uzh.ch>
License: LGPL-3.0-or-later
Requires-Python: >=3.10
